password_generator_subingeorge123/__init__.py
password_generator_subingeorge123/generator.py
password_generator_subingeorge123-0.0.2.dist-info/METADATA
password_generator_subingeorge123-0.0.2.dist-info/WHEEL
password_generator_subingeorge123-0.0.2.dist-info/licenses/LICENSE
password_generator_subingeorge123-0.0.2.dist-info/RECORD
