Metadata-Version: 2.4
Name: password_generator_subingeorge123
Version: 0.0.2
Summary: A small Password Generator package
Author-email: Subin George <subin.vizhalil@gmail.com>
License-File: LICENSE
Classifier: License :: OSI Approved :: MIT License
Classifier: Operating System :: OS Independent
Classifier: Programming Language :: Python :: 3
Requires-Python: >=3.7
